hakarl/__init__.py
hakarl/library.py
hakarl/models.py
hakarl/parsing.py
hakarl/py.typed
hakarl/rendering.py
hakarl/slugify.py
hakarl/util.py
hakarl-0.1.0.dist-info/METADATA
hakarl-0.1.0.dist-info/WHEEL
hakarl-0.1.0.dist-info/licenses/LICENSE
hakarl-0.1.0.dist-info/RECORD
