Metadata-Version: 2.4
Name: hakarl
Version: 0.1.0
Summary: Add your description here
Author-email: Kyle Kestell <kyle@kestell.org>
License-File: LICENSE
Requires-Python: >=3.12
Requires-Dist: lark>=1.2.2
